setup.py
umls_auth/__init__.py
umls_auth/umls_auth.py
umls_auth.egg-info/PKG-INFO
umls_auth.egg-info/SOURCES.txt
umls_auth.egg-info/dependency_links.txt
umls_auth.egg-info/not-zip-safe
umls_auth.egg-info/requires.txt
umls_auth.egg-info/top_level.txt